avell_a52/__init__.py
avell_a52/driver/Ite8291v2.py
avell_a52/driver/__init__.py
avell_a52/driver/actions.py
avell_a52/driver/utils.py
avell_a52-1.0.2.data/scripts/lightkeys
avell_a52-1.0.2.dist-info/METADATA
avell_a52-1.0.2.dist-info/WHEEL
avell_a52-1.0.2.dist-info/top_level.txt
avell_a52-1.0.2.dist-info/RECORD
