Metadata-Version: 2.1
Name: avell-a52
Version: 1.0.2
Summary: A Project to provide a driver and interface to control keyboard rgb led of ITE 8291 V0.2 like Avell laptops
Home-page: https://github.com/petryx/avell-a52-lights
Author: Petryx
Author-email: marlonpetry@gmail.com
License: MIT
Project-URL: Bug Reports, https://github.com/petryx/avell-a52-lights/issues
Project-URL: Source, https://github.com/petryx/avell-a52-lights
Platform: UNKNOWN
Classifier: Programming Language :: Python :: 3
Classifier: License :: OSI Approved :: MIT License
Classifier: Operating System :: POSIX :: Linux
Requires-Dist: pyusb
